nbconvert_a11y/__init__.py
nbconvert_a11y/__main__.py
nbconvert_a11y/_version.py
nbconvert_a11y/audit.py
nbconvert_a11y/exporter.py
nbconvert_a11y/outputs.css
nbconvert_a11y/outputs.py
nbconvert_a11y/pytest_axe.py
nbconvert_a11y/pytest_github_step_summary.py
nbconvert_a11y/pytest_w3c.py
nbconvert_a11y/tables.py
nbconvert_a11y/templates/a11y/README.md
nbconvert_a11y/templates/a11y/base.html.j2
nbconvert_a11y/templates/a11y/list.html.j2
nbconvert_a11y/templates/a11y/section.html.j2
nbconvert_a11y/templates/a11y/table.html.j2
nbconvert_a11y/templates/a11y/components/audit.html.j2
nbconvert_a11y/templates/a11y/components/cell.html.j2
nbconvert_a11y/templates/a11y/components/core.html.j2
nbconvert_a11y/templates/a11y/components/displays.html.j2
nbconvert_a11y/templates/a11y/components/help.html.j2
nbconvert_a11y/templates/a11y/components/inputs.html.j2
nbconvert_a11y/templates/a11y/components/nb-summary.html.j2
nbconvert_a11y/templates/a11y/components/nb-toolbar.html.j2
nbconvert_a11y/templates/a11y/components/sa11y.html.j2
nbconvert_a11y/templates/a11y/components/settings.html.j2
nbconvert_a11y/templates/a11y/components/toc.html.j2
nbconvert_a11y/templates/a11y/components/visibility.html.j2
nbconvert_a11y/templates/a11y/static/settings.js
nbconvert_a11y/templates/a11y/static/settings.jsonschema
nbconvert_a11y/templates/a11y/static/style.css
nbconvert_a11y/templates/a11y/static/theme/__main__.py
nbconvert_a11y/templates/a11y/static/theme/a11y-dark.css
nbconvert_a11y/templates/a11y/static/theme/a11y-high-contrast-dark.css
nbconvert_a11y/templates/a11y/static/theme/a11y-high-contrast-light.css
nbconvert_a11y/templates/a11y/static/theme/a11y-light.css
nbconvert_a11y/templates/a11y/static/theme/blinds-dark.css
nbconvert_a11y/templates/a11y/static/theme/blinds-light.css
nbconvert_a11y/templates/a11y/static/theme/github-dark-colorblind.css
nbconvert_a11y/templates/a11y/static/theme/github-dark-high-contrast.css
nbconvert_a11y/templates/a11y/static/theme/github-dark.css
nbconvert_a11y-2024.3.25.dist-info/METADATA
nbconvert_a11y-2024.3.25.dist-info/WHEEL
nbconvert_a11y-2024.3.25.dist-info/entry_points.txt
nbconvert_a11y-2024.3.25.dist-info/licenses/LICENSE
nbconvert_a11y-2024.3.25.dist-info/RECORD
